setup.cfg
setup.py
xdjango/__init__.py
xdjango/shorcuts.py
xdjango/urls.py
xdjango.egg-info/PKG-INFO
xdjango.egg-info/SOURCES.txt
xdjango.egg-info/dependency_links.txt
xdjango.egg-info/not-zip-safe
xdjango.egg-info/requires.txt
xdjango.egg-info/top_level.txt
xdjango/contrib/__init__.py
xdjango/contrib/auth/__init__.py
xdjango/contrib/auth/backends.py
xdjango/contrib/auth/decorators.py
xdjango/contrib/auth/mixins.py
xdjango/contrib/auth/models.py
xdjango/contrib/auth/permissions.py
xdjango/contrib/auth/responses.py
xdjango/contrib/auth/serializers.py
xdjango/contrib/auth/tokens.py
xdjango/contrib/auth/validators.py
xdjango/contrib/auth/views.py
xdjango/contrib/captcha/__init__.py
xdjango/contrib/captcha/recaptcha.py
xdjango/core/__init__.py
xdjango/core/validators.py
xdjango/core/sms/__init__.py
xdjango/core/sms/backends/__init__.py
xdjango/core/sms/backends/txtlocal.py
xdjango/db/__init__.py
xdjango/db/models/__init__.py
xdjango/db/models/managers.py
xdjango/db/models/fields/__init__.py
xdjango/forms/__init__.py
xdjango/forms/fields.py
xdjango/forms/validators.py
xdjango/models/__init__.py