Metadata-Version: 1.1
Name: xdjango
Version: 0.3.16
Summary: Xtra-django library
Home-page: https://bitbucket.org/projectx-team/xdjango
Author: Ivan Martin
Author-email: ivanmar_91@hotmail.com
License: UNKNOWN
Platform: UNKNOWN
Classifier: Environment :: Web Environment
Classifier: Framework :: Django
Classifier: Intended Audience :: Developers
Classifier: License :: OSI Approved :: GNU Library or Lesser General Public License (LGPL)
Classifier: Operating System :: OS Independent
Classifier: Programming Language :: Python
Classifier: Programming Language :: Python :: 3
